bulk_user_upload/__init__.py
bulk_user_upload/admin.py
bulk_user_upload/forms.py
bulk_user_upload/settings.py
bulk_user_upload/utils.py
bulk_user_upload/static/js/alert-util.js
bulk_user_upload/static/js/c-is-for-cookie.js
bulk_user_upload/static/js/dynamic-html-util.js
bulk_user_upload/static/js/popup-util.js
bulk_user_upload/templates/admin/bulk_upload_users.html
bulk_user_upload/templates/admin/users_change_list.html
bulk_user_upload/templates/email/account_creation_email.html
sample_project/__init__.py
sample_project/manage.py
sample_project/sample_project/__init__.py
sample_project/sample_project/asgi.py
sample_project/sample_project/settings.py
sample_project/sample_project/urls.py
sample_project/sample_project/wsgi.py
sample_project/users/__init__.py
sample_project/users/admin.py
sample_project/users/bulk_user_upload_customizations.py
sample_project/users/managers.py
sample_project/users/models.py
sample_project/users/migrations/0001_initial.py
sample_project/users/migrations/0002_initial_users.py
sample_project/users/migrations/__init__.py
django_bulk_user_upload-0.1.0.dist-info/LICENSE.txt
django_bulk_user_upload-0.1.0.dist-info/METADATA
django_bulk_user_upload-0.1.0.dist-info/WHEEL
django_bulk_user_upload-0.1.0.dist-info/top_level.txt
django_bulk_user_upload-0.1.0.dist-info/RECORD
