Metadata-Version: 2.1
Name: django-bulk-user-upload
Version: 0.1.0
Summary: Installable Django admin interface for bulk user creation from uploaded CSV file.
Home-page: https://github.com/CorrDyn/django-bulk-user-upload
Author: JP Jorissen
License: MIT
Platform: UNKNOWN
Classifier: Development Status :: 3 - Alpha
Classifier: Environment :: Web Environment
Classifier: Framework :: Django
Classifier: Intended Audience :: Developers
Classifier: License :: OSI Approved :: MIT License
Classifier: Operating System :: OS Independent
Classifier: Programming Language :: Python
Classifier: Programming Language :: Python :: 3
Classifier: Programming Language :: Python :: 3.6
Classifier: Programming Language :: Python :: 3.7
Classifier: Programming Language :: Python :: 3.8
Classifier: Programming Language :: Python :: 3.9
Classifier: Programming Language :: Python :: 3 :: Only
Classifier: Topic :: Internet :: WWW/HTTP
Requires-Python: >=3.6
License-File: LICENSE.txt
Requires-Dist: django
Requires-Dist: pandas
